elasticitypy/__init__.py
elasticitypy/dom.py
elasticitypy/elasticitypy.cp310-win_amd64.pyd
elasticitypy/elasticitypy.cp36-win_amd64.pyd
elasticitypy/elasticitypy.cp39-win_amd64.pyd
elasticitypy/expr.py
elasticitypy/mesh.py
elasticitypy/seq.py
elasticitypy-0.0.7.data/data/README/README.md
elasticitypy-0.0.7.data/data/licenses/APACHE2
elasticitypy-0.0.7.data/data/licenses/MIT
elasticitypy-0.0.7.dist-info/LICENSE
elasticitypy-0.0.7.dist-info/METADATA
elasticitypy-0.0.7.dist-info/WHEEL
elasticitypy-0.0.7.dist-info/top_level.txt
elasticitypy-0.0.7.dist-info/RECORD
