Metadata-Version: 2.1
Name: elasticitypy
Version: 0.0.7
Summary: UNKNOWN
Home-page: UNKNOWN
License: GNU LGPLv3
Platform: UNKNOWN
Classifier: License :: OSI Approved :: GNU Lesser General Public License v3 (LGPLv3)
Classifier: Intended Audience :: Science/Research
Classifier: Programming Language :: Rust
Classifier: Programming Language :: Python :: 3
Classifier: Development Status :: 3 - Alpha
Classifier: Operating System :: Microsoft :: Windows
Requires-Python: >=3.9
License-File: LICENSE
